docs/conf.py
osbng/__init__.py
osbng/bng_reference.py
osbng/errors.py
osbng/grids.py
osbng/hierarchy.py
osbng/indexing.py
osbng/indexing_gpd.py
osbng/resolution.py
osbng/traversal.py
osbng/utils.py
osbng-0.5.1.dist-info/licenses/LICENSE
tests/__init__.py
tests/test_bng_reference.py
tests/test_hierarchy.py
tests/test_indexing.py
tests/test_indexing_gpd.py
tests/test_traversal.py
osbng-0.5.1.dist-info/METADATA
osbng-0.5.1.dist-info/WHEEL
osbng-0.5.1.dist-info/top_level.txt
osbng-0.5.1.dist-info/RECORD
