Metadata-Version: 2.4
Name: osbng
Version: 0.5.1
Summary: A Python package supporting geospatial grid indexing and interaction with Ordnance Survey's British National Grid index system
Author-email: Steve Kingston <steve.kingston@os.uk>, Kate New <kate.new@os.uk>, Tom Peterken <tom.peterken@os.uk>, Chris Jochem <chris.jochem@os.uk>, Lucy Main <lucy.main@os.uk>
License-Expression: MIT
Project-URL: Homepage, https://github.com/OrdnanceSurvey/osbng-py
Project-URL: Documentation, https://osbng-py.readthedocs.io/en/stable/
Project-URL: Repository, https://github.com/OrdnanceSurvey/osbng-py
Keywords: geospatial,gis,grid,indexing,spatial
Classifier: Development Status :: 4 - Beta
Classifier: Intended Audience :: Developers
Classifier: Intended Audience :: Science/Research
Classifier: Operating System :: OS Independent
Classifier: Programming Language :: Python :: 3
Classifier: Programming Language :: Python :: 3.11
Classifier: Programming Language :: Python :: 3.12
Classifier: Programming Language :: Python :: 3.13
Classifier: Programming Language :: Python :: 3.14
Classifier: Topic :: Scientific/Engineering :: GIS
Requires-Python: <3.15,>=3.11
License-File: LICENSE
Requires-Dist: numpy>=1.24
Requires-Dist: shapely>=2.0
Provides-Extra: geopandas
Requires-Dist: geopandas>=1.0; extra == "geopandas"
Provides-Extra: docs
Requires-Dist: pydata-sphinx-theme>=0.16; extra == "docs"
Requires-Dist: nbsphinx>=0.9; extra == "docs"
Requires-Dist: sphinx>=8.2; extra == "docs"
Requires-Dist: sphinx-copybutton>=0.5; extra == "docs"
Provides-Extra: test
Requires-Dist: coverage>=7.13; extra == "test"
Requires-Dist: geopandas>=1.0; extra == "test"
Requires-Dist: pytest>=8.0; extra == "test"
Provides-Extra: lint
Requires-Dist: ruff>=0.14; extra == "lint"
Provides-Extra: ci
Requires-Dist: tox>=4.26; extra == "ci"
Provides-Extra: all
Requires-Dist: geopandas>=1.0; extra == "all"
Requires-Dist: matplotlib>=3.7; extra == "all"
Provides-Extra: dev
Requires-Dist: osbng[all,ci,docs,lint,test]; extra == "dev"
Dynamic: license-file
